openapi_qase_suite_generator/__init__.py
openapi_qase_suite_generator/__version.py
openapi_qase_suite_generator/main.py
openapi_qase_suite_generator-1.0.4.dist-info/LICENSE
openapi_qase_suite_generator-1.0.4.dist-info/METADATA
openapi_qase_suite_generator-1.0.4.dist-info/WHEEL
openapi_qase_suite_generator-1.0.4.dist-info/entry_points.txt
openapi_qase_suite_generator-1.0.4.dist-info/top_level.txt
openapi_qase_suite_generator-1.0.4.dist-info/RECORD
