Metadata-Version: 2.1
Name: openapi_qase_suite_generator
Version: 1.0.4
Summary: Generate Qase test suites from OpenAPI specs
Author-email: Example Author <author@example.com>
License: MIT License
Project-URL: Homepage, https://github.com/petrabarus/openapi_qase_suite_generator
Project-URL: Issues, https://github.com/petrabarus/openapi_qase_suite_generator/issues
Keywords: qase,openapi,testsuite
Classifier: Programming Language :: Python :: 3
Classifier: License :: OSI Approved :: MIT License
Classifier: Operating System :: OS Independent
Requires-Python: >=3.8
License-File: LICENSE
Requires-Dist: requests>=2.32.3
Requires-Dist: PyYAML>=6.0.1
